ouseful_nhs_datasupply/__init__.py
ouseful_nhs_datasupply/cli.py
ouseful_nhs_datasupply/nhs_digital_ods.py
ouseful_nhs_datasupply/data/nhsdigitalods.json
ouseful_nhs_datasupply-0.3.1.dist-info/LICENSE
ouseful_nhs_datasupply-0.3.1.dist-info/METADATA
ouseful_nhs_datasupply-0.3.1.dist-info/WHEEL
ouseful_nhs_datasupply-0.3.1.dist-info/entry_points.txt
ouseful_nhs_datasupply-0.3.1.dist-info/top_level.txt
ouseful_nhs_datasupply-0.3.1.dist-info/RECORD
